{
  "mainnet": {
    "tokens": {
      "terra1u0t35drzyy0mujj8rkdyzhe264uls4ug3wdp3x": {
        "protocol": "Anchor",
        "symbol": "bLUNA",
        "token": "terra1u0t35drzyy0mujj8rkdyzhe264uls4ug3wdp3x",
        "icon": "/bLuna.svg"
      },
      "uluna": {
        "protocol": "Native",
        "symbol": "LUNA",
        "token": "uluna",
        "icon": "https://whitelist.mirror.finance/images/Luna.png"
      },
      "uusd": {
        "protocol": "Native",
        "symbol": "UST",
        "token": "uusd",
        "icon": "https://whitelist.mirror.finance/images/UST.png"
      },
      "terra1php5m8a6qd68z02t3zpw4jv2pj4vgw4wz0t8mz": {
        "protocol": "WhiteWhale",
        "symbol": "Whale",
        "token": "terra1php5m8a6qd68z02t3zpw4jv2pj4vgw4wz0t8mz",
        "icon": "/whale.svg"
      },
      "terra17pqpurglgfqnvkhypask28c3llnf69cstaquke": {
        "protocol": "WhiteWhale",
        "symbol": "WHALE-UST LP",
        "token": "terra17pqpurglgfqnvkhypask28c3llnf69cstaquke",
        "icon": "/whale.svg"
      },
      "terra1w0p5zre38ecdy3ez8efd5h9fvgum5s206xknrg": {
        "protocol": "White Whale vUST",
        "symbol": "vUST",
        "token": "terra1w0p5zre38ecdy3ez8efd5h9fvgum5s206xknrg",
        "icon": "/vustlogo.webp"
      }
    },
    "pairs": [
      {
        "contract_addr": "terra12arl49w7t4xpq7krtv43t3dg6g8kn2xxyaav56",
        "liquidity_token": "terra1w0p5zre38ecdy3ez8efd5h9fvgum5s206xknrg",
        "asset_infos": [
          {
            "token": {
              "contract_addr": "terra1php5m8a6qd68z02t3zpw4jv2pj4vgw4wz0t8mz"
            }
          },
          {
            "token": {
              "contract_addr": "terra1w0p5zre38ecdy3ez8efd5h9fvgum5s206xknrg"
            }
          }
        ]
      }
    ]
  },
  "testnet": {
    "tokens": {
      "terra1u0t35drzyy0mujj8rkdyzhe264uls4ug3wdp3x": {
        "protocol": "Anchor",
        "symbol": "bLUNA",
        "token": "terra1u0t35drzyy0mujj8rkdyzhe264uls4ug3wdp3x",
        "icon": "/bLuna.svg"
      },
      "uluna": {
        "protocol": "Native",
        "symbol": "LUNA",
        "token": "uluna",
        "icon": "https://whitelist.mirror.finance/images/Luna.png"
      },
      "uusd": {
        "protocol": "Native",
        "symbol": "UST",
        "token": "uusd",
        "icon": "https://whitelist.mirror.finance/images/UST.png"
      },
      "terra183cvzy6knvva6mpvzcq86uyfxw0nd4925m0d0m": {
        "protocol": "WhiteWhale",
        "symbol": "WHALE",
        "token": "terra183cvzy6knvva6mpvzcq86uyfxw0nd4925m0d0m",
        "icon": "/whale.svg"
      },
      "terra1zuspxvj76ngktnjuawmckpsmynwuvusdnq0pxd": {
        "protocol": "WhiteWhale",
        "symbol": "WHALE-UST LP",
        "token": "terra1zuspxvj76ngktnjuawmckpsmynwuvusdnq0pxd",
        "icon": "/whale.svg"
      },
      "terra1z4hyc87tuln35nu465d5equke4nf7xqepx7rtg": {
        "protocol": "White Whale vUST",
        "symbol": "vUST",
        "token": "terra1z4hyc87tuln35nu465d5equke4nf7xqepx7rtg",
        "icon": "/vustlogo.webp"
      }
    },
    "pairs": [
      {
        "contract_addr": "terra156v8s539wtz0sjpn8y8a8lfg8fhmwa7fy22aff",
        "liquidity_token": "terra1srf30cs8ax73y59gm64lkztnx0zexl8fpv3kx2",
        "asset_infos": [
          {
            "native_token": {
              "denom": "uusd"
            }
          },
          {
            "native_token": {
              "denom": "uluna"
            }
          }
        ]
      },
      {
        "contract_addr": "terra1wq58ty8ddkeav64678tjrhyt7n6xfzqx5kxaej",
        "liquidity_token": "terra1z4hyc87tuln35nu465d5equke4nf7xqepx7rtg",
        "asset_infos": [
          {
            "token": {
              "contract_addr": "terra183cvzy6knvva6mpvzcq86uyfxw0nd4925m0d0m"
            }
          },
          {
            "token": {
              "contract_addr": "terra1z4hyc87tuln35nu465d5equke4nf7xqepx7rtg"
            }
          }
        ]
      }
    ]
  }
}
